tailwind_cp/__init__.py
tailwind_cp/main.py
tailwind_color_picker-0.1.2.dist-info/LICENSE
tailwind_color_picker-0.1.2.dist-info/WHEEL
tailwind_color_picker-0.1.2.dist-info/entry_points.txt
tailwind_color_picker-0.1.2.dist-info/METADATA
tailwind_color_picker-0.1.2.dist-info/RECORD
