Metadata-Version: 2.1
Name: tailwind-color-picker
Version: 0.1.2
Summary: TUI Application for browsing and copying Tailwind colors to the clipboard.
Home-page: https://github.com/1dancook/tailwind-color-picker
Author: Dan Cook
Author-email: cook.r.dan@gmail.com
Requires-Python: >=3.10,<4.0
Classifier: Programming Language :: Python :: 3
Classifier: Programming Language :: Python :: 3.10
Classifier: Programming Language :: Python :: 3.11
Requires-Dist: pyperclip (>=1.8.2,<2.0.0)
Requires-Dist: rich (>=13.6.0,<14.0.0)
Requires-Dist: textual (>=0.41.0,<0.42.0)
Project-URL: Repository, https://github.com/1dancook/tailwind-color-picker
